labs_sphinx_theme/__init__.py
labs_sphinx_theme/layout.html
labs_sphinx_theme/theme.toml
labs_sphinx_theme/components/contact.html
labs_sphinx_theme/components/edit-this-page.html
labs_sphinx_theme/components/footer-links.html
labs_sphinx_theme/components/navbar-version.html
labs_sphinx_theme/static/css/style.css
labs_sphinx_theme-0.16.0.dist-info/entry_points.txt
labs_sphinx_theme-0.16.0.dist-info/licenses/LICENSE
labs_sphinx_theme-0.16.0.dist-info/WHEEL
labs_sphinx_theme-0.16.0.dist-info/METADATA
labs_sphinx_theme-0.16.0.dist-info/RECORD
