Metadata-Version: 2.4
Name: labs-sphinx-theme
Version: 0.16.0
Summary: A thin sphinx theme to customize pydata-sphinx-theme consistently across PyMC-Labs projects.
Author-email: PyMC Labs <info@pymc-labs.com>
Requires-Python: >=3.9
Classifier: Development Status :: 3 - Alpha
Classifier: Intended Audience :: Developers
Classifier: License :: OSI Approved :: Apache Software License
Classifier: Operating System :: OS Independent
Classifier: Programming Language :: Python
Classifier: Programming Language :: Python :: 3
Classifier: Programming Language :: Python :: 3.8
Classifier: Programming Language :: Python :: 3.9
Classifier: Programming Language :: Python :: 3.10
Classifier: Programming Language :: Python :: 3.11
License-File: LICENSE
Requires-Dist: pydata-sphinx-theme>=0.16.0,<0.17
Requires-Dist: sphinx>=5
Project-URL: documentation, https://www.pymc-labs.com
Project-URL: source, https://github.com/pymc-labs/labs-sphinx-theme
Project-URL: tracker, https://github.com/pymc-labs/labs-sphinx-theme/issues
